_skycoin.cpython-37m-darwin.so
skycoin/__init__.py
skycoin/skycoin.py
tests/utils/__init__.py
tests/utils/transutil.py
pyskycoin-0.26.0.dist-info/LICENSE.txt
pyskycoin-0.26.0.dist-info/METADATA
pyskycoin-0.26.0.dist-info/WHEEL
pyskycoin-0.26.0.dist-info/entry_points.txt
pyskycoin-0.26.0.dist-info/top_level.txt
pyskycoin-0.26.0.dist-info/RECORD
