Metadata-Version: 2.1
Name: pyskycoin
Version: 0.26.0
Summary: Skycoin Python Library
Home-page: https://github.com/skycoin/pyskycoin
Author: Ratmil Torres
Author-email: skycoin@simelo.tech
License: UNKNOWN
Keywords: skycoin crypto coin currency blockchain
Platform: UNKNOWN
Classifier: Development Status :: 3 - Alpha
Classifier: Intended Audience :: Developers
Classifier: License :: OSI Approved :: MIT License
Classifier: Programming Language :: Python :: 2
Classifier: Programming Language :: Python :: 2.7
Classifier: Programming Language :: Python :: 3
Classifier: Programming Language :: Python :: 3.4
Classifier: Programming Language :: Python :: 3.5
Classifier: Programming Language :: Python :: 3.6
Classifier: Programming Language :: Python :: 3.7
Provides-Extra: test
Provides-Extra: dev
